Metadata-Version: 1.1
Name: vassal-deployer
Version: 0.0.2
Summary: uwsgi and nginx flask app vassal manager for containers
Home-page: https://github.com/evansde77/vassal_deployer
Author: evansde77
Author-email: evansde77.github@gmail.com
License: UNKNOWN
Platform: UNKNOWN
Provides: vassal_deployer
